{
  "version": 2,
  "extractor": "pdffigures2",
  "figures": [
    {
      "url": "assets/figures/biorxiv/biorxiv-10-64898-2026-04-08-717299-v1/fig-001.webp",
      "caption": "Figure 3 Proportion of genetic risk mediated by brain imaging-derived phenotypes. Top IDPs ranked by proportion mediated for each outcome. Across all outcomes, the absolute proportion mediated is small (generally < 2%). Alcohol initiation shows consistently negative mediation effects, indicating a buffering pattern. Any-substance initiation shows mixed positive and negative effects, while cannabis and nicotine show small and non-significant mediation. These results indicate that baseline brain features explain only a minimal proportion of genetic liability.",
      "page": 8,
      "index": 1,
      "width": 1096,
      "height": 689
    },
    {
      "url": "assets/figures/biorxiv/biorxiv-10-64898-2026-04-08-717299-v1/fig-002.webp",
      "caption": "Figure 1 Direct versus mediated effects of externalizing polygenic risk across substance initiation outcomes. Scatter plots show the relationship between the direct effect (ADE; x-axis) and indirect (mediated) effect (ACME; y-axis) for each outcome (alcohol, any substance, cannabis, nicotine). Each point represents a neuroimaging-derived phenotype (IDP). Points are colored by mediation significance (ACME FDR < 0.05, ACME p < 0.05, or not significant). Across all outcomes, ADE is substantially larger than ACME, with ACME values close to zero (on the order of 10−4). This separation indicates that genetic liability primarily influences substance initiation through direct pathways rather than through baseline brain imaging measures. Selected top IDPs are labeled for interpretability.",
      "page": 6,
      "index": 2,
      "width": 1096,
      "height": 781
    }
  ]
}